[
  {
    "id": 1,
    "name": "Steph",
    "image": "https://usatftw.files.wordpress.com/2019/12/getobject-47-e1575408347332.jpeg?w=779&h=467&crop=1&zoom=2"
  },
  {
    "id": 2,
    "name": "Demar",
    "image": "https://img.bleacherreport.net/img/slides/photos/004/366/012/d36e20b78327de9e1ff16a3df00e4a24_crop_exact.jpg?h=533&w=800&q=70&crop_x=center&crop_y=top"
  },
  {
    "id": 3,
    "name": "Dame",
    "image": "https://imagesvc.timeincapp.com/v3/fan/image?url=https://valleyofthesuns.com/wp-content/uploads/getty-images/2017/07/1140654574.jpeg&w=3200"
  },
  {
    "id": 4,
    "name": "Trey",
    "image": "https://res-4.cloudinary.com/ybmedia/image/upload/c_crop,h_1068,w_1902,x_0,y_65/c_fill,f_auto,h_495,q_auto,w_880/v1/m/1/2/124200238e85cc29d394f41df8e5a7bb55e48876/13653123.jpg"
  },

  {
    "id": 5,
    "name": "James",
    "image": "http://www.wruf.com/wp-content/uploads/2019/04/james-harden-cropped_adrrcka6po2g1feaaueg721vj-660x330.jpg"
  },
  {
    "id": 6,
    "name": "Luka",
    "image": "https://res-4.cloudinary.com/ybmedia/image/upload/c_crop,h_517,w_920,x_274,y_129/c_fill,f_auto,h_495,q_auto,w_880/v1/m/c/a/cac4bd184d8c037de8d1efc850cde9c07adad922/12057810.jpg"
  },
  {
    "id": 7,
    "name": "Kyrie",
    "image": "https://lastwordonprobasketball.com/wp-content/uploads/sites/9/2019/11/Kyrie-Irving.jpg"
  },
  {
    "id": 8,
    "name": "Kevin",
    "image": "https://img-s-msn-com.akamaized.net/tenant/amp/entityid/AAIpgpL.img?h=814&w=1248&m=6&q=60&o=f&l=f&x=1807&y=734"
  },
  {
    "id": 9,
    "name": "GreekFreek",
    "image": "https://usatftw.files.wordpress.com/2017/10/usp_nba__preseason-milwaukee_bucks_at_chicago_bull_94389403.jpg?w=779&h=467&crop=1&zoom=2"
  },
  {
    "id": 10,
    "name": "Bron",
    "image": "https://sportsnaut.com/wp-content/uploads/2018/10/IMG_2683.jpg"
  }
]